rotest_progress/__init__.py
rotest_progress/current_progress.py
rotest_progress/full_progress.py
rotest_progress/popup_progress.py
rotest_progress/utils.py
rotest_progress-0.2.1.dist-info/METADATA
rotest_progress-0.2.1.dist-info/WHEEL
rotest_progress-0.2.1.dist-info/entry_points.txt
rotest_progress-0.2.1.dist-info/top_level.txt
rotest_progress-0.2.1.dist-info/RECORD
